causalgen/__init__.py
causalgen/generator.py
causalgen/variables.py
causalgen-0.1.4.dist-info/METADATA
causalgen-0.1.4.dist-info/WHEEL
causalgen-0.1.4.dist-info/licenses/LICENSE
causalgen-0.1.4.dist-info/RECORD
