Metadata-Version: 2.4
Name: causalgen
Version: 0.1.4
Summary: Causalgen: a causal-based utility for data generation
Project-URL: Repository, https://github.com/giuluck/causalgen/
Author: University of Bologna - DISI
Author-email: Luca Giuliani <luca.giuliani13@unibo.it>
Maintainer-email: Luca Giuliani <luca.giuliani13@unibo.it>
License-Expression: MIT
License-File: LICENSE
Classifier: Development Status :: 4 - Beta
Classifier: License :: OSI Approved :: MIT License
Classifier: Operating System :: OS Independent
Classifier: Programming Language :: Python
Requires-Python: >=3.8
Requires-Dist: matplotlib>=3.7
Requires-Dist: networkx>=3.0
Requires-Dist: numpy>=1.22
Requires-Dist: pandas>=1.4
